{
  "530": {
    "titre": "CU VELODROME",
    "url": "https://trouverunlogement.lescrous.fr/tools/47/accommodations/530"
  },
  "687": {
    "titre": "CU JEAN MONNET",
    "url": "https://trouverunlogement.lescrous.fr/tools/47/accommodations/687"
  },
  "2993": {
    "titre": "CU BRIDOUX",
    "url": "https://trouverunlogement.lescrous.fr/tools/47/accommodations/2993"
  },
  "2102": {
    "titre": "CU Lann-Trussac",
    "url": "https://trouverunlogement.lescrous.fr/tools/47/accommodations/2102"
  },
  "2608": {
    "titre": "BOSQUET",
    "url": "https://trouverunlogement.lescrous.fr/tools/47/accommodations/2608"
  },
  "2688": {
    "titre": "GALILEE",
    "url": "https://trouverunlogement.lescrous.fr/tools/47/accommodations/2688"
  },
  "1521": {
    "titre": "Residence Pascal Paoli 1",
    "url": "https://trouverunlogement.lescrous.fr/tools/47/accommodations/1521"
  },
  "1995": {
    "titre": "Residence Pierrette Grimaldi",
    "url": "https://trouverunlogement.lescrous.fr/tools/47/accommodations/1995"
  },
  "522": {
    "titre": "LE VELUM",
    "url": "https://trouverunlogement.lescrous.fr/tools/47/accommodations/522"
  },
  "2191": {
    "titre": "TANNERIES",
    "url": "https://trouverunlogement.lescrous.fr/tools/47/accommodations/2191"
  },
  "516": {
    "titre": "LE VELUM",
    "url": "https://trouverunlogement.lescrous.fr/tools/47/accommodations/516"
  },
  "1458": {
    "titre": "Residence Pascal MARTIN",
    "url": "https://trouverunlogement.lescrous.fr/tools/47/accommodations/1458"
  },
  "1061": {
    "titre": "DR DESFRAY",
    "url": "https://trouverunlogement.lescrous.fr/tools/47/accommodations/1061"
  },
  "1224": {
    "titre": "BAZEILLES",
    "url": "https://trouverunlogement.lescrous.fr/tools/47/accommodations/1224"
  },
  "1567": {
    "titre": "MAISON DES ETUDIANTS",
    "url": "https://trouverunlogement.lescrous.fr/tools/47/accommodations/1567"
  },
  "506": {
    "titre": "LE VELUM",
    "url": "https://trouverunlogement.lescrous.fr/tools/47/accommodations/506"
  },
  "3106": {
    "titre": "Résidence de Felletin",
    "url": "https://trouverunlogement.lescrous.fr/tools/47/accommodations/3106"
  },
  "1211": {
    "titre": "BAZEILLES",
    "url": "https://trouverunlogement.lescrous.fr/tools/47/accommodations/1211"
  },
  "291": {
    "titre": "Résidence de Brive",
    "url": "https://trouverunlogement.lescrous.fr/tools/47/accommodations/291"
  },
  "3142": {
    "titre": "LOUISE ET COLETTE PERIES",
    "url": "https://trouverunlogement.lescrous.fr/tools/47/accommodations/3142"
  },
  "910": {
    "titre": "Residence Pierrette Grimaldi",
    "url": "https://trouverunlogement.lescrous.fr/tools/47/accommodations/910"
  },
  "1491": {
    "titre": "La GRAVIERE",
    "url": "https://trouverunlogement.lescrous.fr/tools/47/accommodations/1491"
  },
  "494": {
    "titre": "LE THELEME",
    "url": "https://trouverunlogement.lescrous.fr/tools/47/accommodations/494"
  },
  "2789": {
    "titre": "Residence Farrandu ETTORI",
    "url": "https://trouverunlogement.lescrous.fr/tools/47/accommodations/2789"
  }
}